Doric/MultiBlock.py
Doric/MultiBlockReducers.py
Doric/ProgBlocks.py
Doric/ProgNet.py
Doric/UtilityBlocks.py
Doric/UtilityFunctions.py
Doric/__init__.py
Doric/extra_blocks/ConvBlocks.py
Doric/extra_blocks/__init__.py
Doric/extra_blocks/deform_conv2d.py
Doric-1.1.1.dist-info/LICENSE.txt
Doric-1.1.1.dist-info/METADATA
Doric-1.1.1.dist-info/WHEEL
Doric-1.1.1.dist-info/top_level.txt
Doric-1.1.1.dist-info/RECORD
