Metadata-Version: 2.1
Name: Doric
Version: 1.1.1
Summary: Doric is a lightweight library for implementing and extending progressive neural networks.
Home-page: https://github.com/arcosin/Doric
Author: Maxwell J. Jacobson
Author-email: jacobs57@purdue.edu
License: MIT
Platform: UNKNOWN
Classifier: License :: OSI Approved :: MIT License
Classifier: Programming Language :: Python :: 3
Classifier: Programming Language :: Python :: 3.7
Requires-Dist: pytorch
